{"children":[{"content":{"src":"/assets/studio-design-asset-files/projects/RQqJk5Zag0/s-1800x1215_v-frms_webp_0290bf2c-236e-4a02-850b-25c9d978aed3.png","type":"image"},"name":"Image","style":{":before":{"filter":"brightness(53%)"},"height":"100vh","left":"0px","position":"fixed","top":"0px","width":"100%","zIndex":"0"},"tagName":"","uuid":"01af6444-b1ef-4a6f-913f-3040a68ac916","children":[]},{"children":[{"content":{"data":"<iframe src=\"https://vimeo.com/event/5438914/embed\" frameborder=\"0\" allow=\"autoplay; fullscreen; picture-in-picture; encrypted-media; web-share\" referrerpolicy=\"strict-origin-when-cross-origin\" allowfullscreen style=\"position:absolute;top:0;left:0;width:100%;height:100%;\"></iframe>","type":"iframe"},"name":"Iframe","style":{"background":"#EEEEEE","borderRadius":"0px","height":"100%","left":"0px","opacity":1,"padding":"0 0 0 0","position":"absolute","top":"0px","width":"100%","zIndex":1},"tagName":"","uuid":"9a52a912-6dc6-42b2-8366-54fb546d132e","children":[]},{"content":{"src":"/assets/studio-design-asset-files/projects/RQqJk5Zag0/s-160x90_df4d5b3e-e994-41c2-b1ca-0092a9e510f2.svg","type":"img"},"name":"Rectangle 42413.svg","style":{"@mobile":{"width":"90vw"},"height":"auto","width":"1400px"},"tagName":"","uuid":"9b1ce110-ad91-4631-905b-9692e66956b7","children":[]}],"name":"<group>","style":{"@mobile":{"justifyContent":"flex-start"},"alignContent":"center","alignItems":"center","flexWrap":"nowrap","justifyContent":"center","margin":"0px 0px 0px 0px","padding":"0px"},"tagName":"div","uuid":"e9657675-c072-4b08-8f6f-b59fe9de9f04"},{"children":[{"action":{"type":"link","val":"2022/sponsor"},"content":{"data":"文字起こしを見る","type":"text"},"link":{"newTab":false,"path":""},"name":"button","style":{"@mobile":{"fontSize":"12px"},"@tablet":{"fontSize":"12px"},"background":"rgba(0,0,0,0.0)","borderBottom":"0px solid #000","borderLeft":"0px solid #000","borderRadius":"0","borderRight":"0px solid #000","borderTop":"0px solid #000","boxShadow":"none","color":"#FFFFFF","flex":"none","fontFamily":"var(--s-font-64b6e965)","fontSize":"14px","fontWeight":"900","height":"auto","letterSpacing":"0.08em","lineHeight":"2","margin":"0 0 0 0","padding":"0px 0px 0px","textAlign":"center","textShadow":"none","width":"auto"},"uuid":"1f4a04be-d123-408a-bd45-304909260381","children":[]},{"content":{"src":"/assets/studio-design-asset-files/projects/RQqJk5Zag0/s-24x24_8ae62438-f399-437d-8375-e9d05cc3774d.svg","type":"img"},"name":"open_in_new_24dp_E3E3E3_FILL0_wght400_GRAD0_opsz24.svg","style":{"height":"auto","width":"16px"},"tagName":"","uuid":"0afe573d-5797-4fe2-9c49-384a2ec1aa74","children":[]}],"content":{"href":"https://vimeo.com/ondemand/designship2022","type":""},"link":{"newTab":true,"path":"https://live.udtalk.jp/a8bc0ec78bfe1389b0852a2bf469ff93aa2f1a3e245ed3c96f4964c2654edb26"},"name":"Box","style":{"@mini":{"display":"flex"},"@mobile":{"margin":"8px 8px 0px 8px"},"@tablet":{"padding":"4px 16px 4px 16px"},"alignContent":"center","alignItems":"center","background":"#db297b","borderRadius":"128px","flexDirection":"row","flexWrap":"nowrap","gap":"8px","height":"auto","justifyContent":"center","margin":"24px 0px 0px 0px","padding":"4px 24px 4px 24px","width":"auto"},"tagName":"","uuid":"ef90baaf-cf74-473f-bb90-33e329ab982c"},{"children":[{"children":[{"content":{"data":"close","type":"icon"},"name":"close","style":{"@tablet":{"fontSize":"16px"},"color":"#ffffff","fontSize":"24px"},"tagName":"","uuid":"1213bde4-8382-415f-96f3-f0f7de159335","children":[]}],"link":{"newTab":false,"path":""},"name":"<group>","style":{"@tablet":{"flex":"none","height":"32px","width":"32px"},"alignContent":"center","alignItems":"center","background":"var(--s-color-c889a519)","borderRadius":"48px","flex":"none","flexWrap":"nowrap","height":"44px","justifyContent":"center","margin":"0px 0px 0px 0px","padding":"8px","width":"44px"},"tagName":"div","uuid":"126d8092-df88-4aa6-87ed-d7144d42ab8a"}],"link":{"newTab":false,"path":"studio-action://modal-close"},"name":"<group>","style":{"alignContent":"flex-end","alignItems":"flex-end","flexWrap":"nowrap","justifyContent":"center","padding":"0px","position":"fixed","right":"40px","top":"40px","width":"auto","zIndex":2},"tagName":"div","uuid":"89bc4b5b-9e25-4d5f-9d42-9103811883aa"}],"content":{"type":""},"name":"Backdrop","style":{"alignContent":"center","alignItems":"center","background":"rgba(0,0,0,0.16)","height":"100%","justifyContent":"center","width":"100%"},"transition":{"opacity":0,"transform":"none"},"uuid":"6f46442c-6d05-47ad-9185-b6f9ff1a524a"}